nyt_games_cli/__init__.py
nyt_games_cli/__main__.py
nyt_games_cli/connections.py
nyt_games_cli/letterboxed.py
nyt_games_cli/main.py
nyt_games_cli/mini_crossword.py
nyt_games_cli/nyt_data.py
nyt_games_cli/spelling_bee.py
nyt_games_cli/strands.py
nyt_games_cli/utils.py
nyt_games_cli/wordle.py
nyt_games_cli-0.0.7.dist-info/LICENSE
nyt_games_cli-0.0.7.dist-info/WHEEL
nyt_games_cli-0.0.7.dist-info/METADATA
nyt_games_cli-0.0.7.dist-info/RECORD
