Metadata-Version: 2.1
Name: nyt-games-cli
Version: 0.0.7
Summary: Python package for playing NYT games on the command line
Author-email: Charlie Dudzik <dudzikc@outlook.com>
Classifier: License :: OSI Approved :: MIT License
Requires-Dist: pycurses<1.0.0
Requires-Dist: playwright>=1.47,<4.0.0
Requires-Dist: requests>=2.0.0,<3.0.0
Requires-Dist: beautifulsoup4>=4.0.0,<5.0.0
Requires-Dist: setproctitle>1.0.0,<2.0.0
